contig_tools/__init__.py
contig_tools/check_metrics.py
contig_tools/co_located.py
contig_tools/contig_metrics.py
contig_tools/file_parsing.py
contig_tools/filter_contigs.py
contig_tools/utility.py
contig_tools/scripts/contig-tools
contig_tools-0.3.9.data/scripts/contig-tools
contig_tools-0.3.9.dist-info/METADATA
contig_tools-0.3.9.dist-info/WHEEL
contig_tools-0.3.9.dist-info/top_level.txt
contig_tools-0.3.9.dist-info/RECORD
