Metadata-Version: 2.1
Name: contig-tools
Version: 0.3.9
Summary: Utility package to parse multi fasta files resulting from de novo assembly
Home-page: UNKNOWN
Author: Anthony Underwood
Author-email: au3@sanger.ac.uk
License: MIT
Platform: UNKNOWN
Classifier: Development Status :: 3 - Alpha
Classifier: Intended Audience :: Science/Research
Classifier: License :: OSI Approved :: MIT License
Classifier: Programming Language :: Python :: 3
Requires-Python: >=3.7
Requires-Dist: biopython
Requires-Dist: colorlog
Requires-Dist: pyyaml
Requires-Dist: parmap
Requires-Dist: tqdm
